{
  "actors": [
    {
      "id": "@rodrigoteamx",
      "kind": "human",
      "principal": null,
      "roles": [
        "owner",
        "maintainer",
        "reviewer"
      ]
    },
    {
      "id": "codex",
      "kind": "agent",
      "principal": "@rodrigoteamx",
      "roles": [
        "author",
        "investigator",
        "producer"
      ]
    },
    {
      "id": "github-actions",
      "kind": "ci",
      "principal": "@rodrigoteamx",
      "roles": [
        "evidence-producer",
        "gate-runner"
      ]
    }
  ],
  "artifacts": [
    {
      "description": "A typed change contract containing scope, claims, criteria, and definition of done.",
      "id": "change-contract-artifact",
      "kind": "artifact",
      "producedBy": "repo:governance-compiler",
      "sourceDecision": "ADR-0003",
      "tier": "enforced"
    },
    {
      "description": "Canonical plan.json and manifest.json generated from the contract.",
      "id": "governance-plan",
      "kind": "artifact",
      "producedBy": "repo:governance-compiler",
      "sourceDecision": "ADR-0003",
      "tier": "enforced"
    },
    {
      "description": "An independent review attached to the proposed change.",
      "id": "review-record",
      "kind": "artifact",
      "producedBy": "github:independent-review",
      "sourceDecision": "ADR-0003",
      "tier": "deferred"
    }
  ],
  "assumptions": [
    {
      "id": "bootstrap-authority",
      "source": "user-directive:2026-07-20",
      "statement": "The initial contract is accepted directly by the project owner before external review enforcement exists."
    },
    {
      "id": "single-maintainer-bootstrap",
      "source": "github-org-observation:2026-07-20",
      "statement": "The organization currently has one human maintainer available to approve governance changes."
    }
  ],
  "decisions": [
    {
      "contentHash": "e502f31f735a167218fc7f1c6af22e7a8a4248e76b06190075ec4076636fcf4b",
      "declaredStatus": "accepted",
      "effectiveStatus": "superseded",
      "id": "ADR-0001",
      "supersededBy": "ADR-0002",
      "title": "Development governance is a deterministic contract"
    },
    {
      "contentHash": "828b33d7262b11255fb0e3dbe121d6d378295743322279e213f3bde0084be0f3",
      "declaredStatus": "accepted",
      "effectiveStatus": "superseded",
      "id": "ADR-0002",
      "supersededBy": "ADR-0003",
      "title": "Signed identity is enforced at the GitHub trust boundary"
    },
    {
      "contentHash": "6c38ca8507ca5ce03f06dca89c4fdfb7a7f1fcb0fada11cd9f3958b6dd20f580",
      "declaredStatus": "accepted",
      "effectiveStatus": "accepted",
      "id": "ADR-0003",
      "supersededBy": null,
      "title": "Product specifications are deterministic contract inputs"
    },
    {
      "contentHash": "69f0500e8ec1fa52ee80fdf1ea149cdf53cfc457d1e36f64bcc5a1aa141e7c11",
      "declaredStatus": "accepted",
      "effectiveStatus": "accepted",
      "id": "ADR-0004",
      "supersededBy": null,
      "title": "OverlayKit is a secure show-centered production studio"
    },
    {
      "contentHash": "2a4b7928ffe16c05f144ba86a4e448afb2118976d7f1d9d68f8dcb6ff98c623f",
      "declaredStatus": "accepted",
      "effectiveStatus": "accepted",
      "id": "ADR-0005",
      "supersededBy": null,
      "title": "Production intents name their target and direct Program authority"
    },
    {
      "contentHash": "39b2c22a3f532ca7db896ecead57710c6f2bf063db7d62d4389451a87b9d769a",
      "declaredStatus": "accepted",
      "effectiveStatus": "accepted",
      "id": "ADR-0006",
      "supersededBy": null,
      "title": "Production cues compose intents with explicit partial outcomes"
    },
    {
      "contentHash": "f4184f5a95871dccf1f5063ed499e873af4610be4e890b10e75f07363f544f34",
      "declaredStatus": "accepted",
      "effectiveStatus": "accepted",
      "id": "ADR-0007",
      "supersededBy": null,
      "title": "Control feedback separates server truth from delivery acknowledgement"
    },
    {
      "contentHash": "713ff82019273526b5ce0f4cdebce565bc095667654abb01ceab040dae488659",
      "declaredStatus": "accepted",
      "effectiveStatus": "accepted",
      "id": "ADR-0008",
      "supersededBy": null,
      "title": "Feedback admission binds signed provenance to device authority"
    },
    {
      "contentHash": "2ddbcde2abb2272a54ab19f8260435db77bca87041ab016efb3bcf9dd60fed32",
      "declaredStatus": "accepted",
      "effectiveStatus": "accepted",
      "id": "ADR-0009",
      "supersededBy": null,
      "title": "Device credential generations bind exact authority"
    },
    {
      "contentHash": "c8455679afcd9cc085a955fc34185f37051ad52e9b8f3edcec315beac723a524",
      "declaredStatus": "accepted",
      "effectiveStatus": "superseded",
      "id": "ADR-0010",
      "supersededBy": "ADR-0027",
      "title": "Device credential persistence is single-instance atomic"
    },
    {
      "contentHash": "74f49336bd776235f2d26a0fdde9b32d6d73fe6427f1766825855c5954b2fff6",
      "declaredStatus": "accepted",
      "effectiveStatus": "accepted",
      "id": "ADR-0011",
      "supersededBy": null,
      "title": "Device bearers use versioned domain-separated verifiers"
    },
    {
      "contentHash": "a0c08ce8a7a2bc92e854de7c5a8f0f7eb9acd0d0e8f221f36a9acf83d9e52750",
      "declaredStatus": "accepted",
      "effectiveStatus": "accepted",
      "id": "ADR-0012",
      "supersededBy": null,
      "title": "Protocol publishes one compiled ESM implementation"
    },
    {
      "contentHash": "ec0869861fb3240bd14d4806f5a5ddfe69496504001b48feac13a72714ca92fe",
      "declaredStatus": "accepted",
      "effectiveStatus": "accepted",
      "id": "ADR-0013",
      "supersededBy": null,
      "title": "Server composes device authority before network listen"
    },
    {
      "contentHash": "859b96e6364f0d5b5c7a361c6ab2b6ee60d5a8d1bd3b6e5e0c523d42f6bb107e",
      "declaredStatus": "accepted",
      "effectiveStatus": "accepted",
      "id": "ADR-0014",
      "supersededBy": null,
      "title": "Device control derives exact authority from route coordinates"
    },
    {
      "contentHash": "2523ae10c813ee7db5e92848355c9a68ab8ee325e9e5321b2ce7ff3f9f1da746",
      "declaredStatus": "accepted",
      "effectiveStatus": "accepted",
      "id": "ADR-0015",
      "supersededBy": null,
      "title": "Action catalogs project capability and authority intersection"
    },
    {
      "contentHash": "e66365f6d3bd6f5eb22b3b9f4caa00d5d90956b737636fa42c04afc4294c04b2",
      "declaredStatus": "accepted",
      "effectiveStatus": "accepted",
      "id": "ADR-0016",
      "supersededBy": null,
      "title": "Device action catalogs are authenticated point-in-time discovery"
    },
    {
      "contentHash": "2a760b6417773e5695811e624d3dab85307cef470b12e677c8ce2cc75cd8107d",
      "declaredStatus": "accepted",
      "effectiveStatus": "accepted",
      "id": "ADR-0017",
      "supersededBy": null,
      "title": "Component visibility feedback derives only from server-known structure"
    },
    {
      "contentHash": "d8da23d10c4fdef03522926feb44981bd488e69285091383dc35d6cc2e48a769",
      "declaredStatus": "accepted",
      "effectiveStatus": "accepted",
      "id": "ADR-0018",
      "supersededBy": null,
      "title": "Apache-2.0 licensing and Rodrigo Vicente attribution are enforced distribution metadata"
    },
    {
      "contentHash": "733201fb5ccbed3879c155d2f92c73bd0fdae67c531fcdc542dc054bfd5ed638",
      "declaredStatus": "accepted",
      "effectiveStatus": "accepted",
      "id": "ADR-0019",
      "supersededBy": null,
      "title": "Device visibility feedback is issued from fresh authority with durable audience sequences"
    },
    {
      "contentHash": "bd502dae3c117272ff41e6e5f20501c591d00b8c1a38562bfeb166d6a8ec883b",
      "declaredStatus": "accepted",
      "effectiveStatus": "accepted",
      "id": "ADR-0020",
      "supersededBy": null,
      "title": "Signed device control frames bind catalog deltas to renewable server truth"
    },
    {
      "contentHash": "56845d8e6b96cae673f1bfc515e3a162f69c5e4cf54e58a8532e58a444bb53df",
      "declaredStatus": "accepted",
      "effectiveStatus": "accepted",
      "id": "ADR-0021",
      "supersededBy": null,
      "title": "Device connection authority is exclusive and retired through linearizable barriers"
    },
    {
      "contentHash": "7dbe40ce3fe1dad9da81e3ab762da3f3fbc5f33a8f34c9239cd97d5a11545563",
      "declaredStatus": "accepted",
      "effectiveStatus": "accepted",
      "id": "ADR-0022",
      "supersededBy": null,
      "title": "Device WebSocket transport authenticates before upgrade and precedes readiness"
    },
    {
      "contentHash": "37c5ba2e83c348ed9db7b859db924018c5f0f53c218b8373f11a67bf790ac2e6",
      "declaredStatus": "accepted",
      "effectiveStatus": "accepted",
      "id": "ADR-0023",
      "supersededBy": null,
      "title": "Device readiness requires current target-complete snapshot application"
    },
    {
      "contentHash": "b458ec80f45d521fb4b07e6ee15694fb722584207e182f0fe128fe16e1c6c086",
      "declaredStatus": "accepted",
      "effectiveStatus": "accepted",
      "id": "ADR-0024",
      "supersededBy": null,
      "title": "Device sequences require exclusive observable durable reservation"
    },
    {
      "contentHash": "3ac1c321155926ed69de98e70a7562a0efcdfc860be282e73e8014f60f6efd34",
      "declaredStatus": "accepted",
      "effectiveStatus": "accepted",
      "id": "ADR-0025",
      "supersededBy": null,
      "title": "Device bootstrap payloads require atomic current signed issuance"
    },
    {
      "contentHash": "2d455c1d43b54da29a0c086115b88015ae045bdd414b4f88c9d845f41810af49",
      "declaredStatus": "accepted",
      "effectiveStatus": "accepted",
      "id": "ADR-0026",
      "supersededBy": null,
      "title": "Device connections require continuously evidenced effective authority"
    },
    {
      "contentHash": "256b9462df26afb578978f1dce12c753837eeb3d7f6ab2e98103085922f2c5f5",
      "declaredStatus": "accepted",
      "effectiveStatus": "accepted",
      "id": "ADR-0027",
      "supersededBy": null,
      "title": "Device credential authority requires exclusive observable SQLite ownership"
    },
    {
      "contentHash": "709e3b38da066c20ab67626c79f896af693ada1a22a1fc61a9dc4e0c0cc3bf81",
      "declaredStatus": "accepted",
      "effectiveStatus": "accepted",
      "id": "ADR-0028",
      "supersededBy": null,
      "title": "Device readiness authority requires durable transition evidence"
    }
  ],
  "engineVersion": "overlaykit-governance-host/v2",
  "gates": [
    {
      "boundTo": "ci:build",
      "description": "Every buildable workspace builds successfully.",
      "id": "build",
      "kind": "gate",
      "outcome": null,
      "sourceDecision": "ADR-0003",
      "tier": "enforced"
    },
    {
      "boundTo": "ci:governance",
      "description": "Typed change contracts satisfy their schema and epistemic invariants.",
      "id": "change-contract",
      "kind": "gate",
      "outcome": null,
      "sourceDecision": "ADR-0003",
      "tier": "enforced"
    },
    {
      "boundTo": "ci:governance",
      "description": "The deterministic governance host validates and verifies the stored plan and manifest.",
      "id": "governance-contract",
      "kind": "gate",
      "outcome": null,
      "sourceDecision": "ADR-0003",
      "tier": "enforced"
    },
    {
      "boundTo": "github:independent-review",
      "description": "A reviewer other than the last producer approves the change.",
      "id": "independent-review",
      "kind": "gate",
      "outcome": null,
      "sourceDecision": "ADR-0003",
      "tier": "deferred"
    },
    {
      "boundTo": "ci:quality",
      "description": "Lint, type-check, and automated tests pass.",
      "id": "quality",
      "kind": "gate",
      "outcome": null,
      "sourceDecision": "ADR-0003",
      "tier": "enforced"
    },
    {
      "boundTo": "ci:signed-identity",
      "description": "The workflow commit and every pull-request commit carry an identity signature verified by the GitHub root of trust.",
      "id": "signed-identity",
      "kind": "gate",
      "outcome": null,
      "sourceDecision": "ADR-0003",
      "tier": "enforced"
    }
  ],
  "mechanisms": [
    {
      "enforcementCapable": true,
      "expectedCommand": "npm run build",
      "id": "ci:build",
      "kind": "github-actions-job",
      "locator": ".github/workflows/governance.yml#jobs.validate",
      "subject": "workspace-builds"
    },
    {
      "enforcementCapable": true,
      "expectedCommand": "npm run governance:observe:github -- --run artifacts/governance-run.json --out artifacts/github-evidence.json --observation-out artifacts/github-observation.json",
      "id": "ci:github-observer",
      "kind": "github-actions-job",
      "locator": ".github/workflows/governance.yml#jobs.observe",
      "subject": "github-root-of-trust-evidence"
    },
    {
      "enforcementCapable": true,
      "expectedCommand": "npm run governance:check",
      "id": "ci:governance",
      "kind": "github-actions-job",
      "locator": ".github/workflows/governance.yml#jobs.validate",
      "subject": "governance-contract"
    },
    {
      "enforcementCapable": true,
      "expectedCommand": "npm run check",
      "id": "ci:quality",
      "kind": "github-actions-job",
      "locator": ".github/workflows/governance.yml#jobs.validate",
      "subject": "source-quality"
    },
    {
      "enforcementCapable": true,
      "expectedCommand": "npm run governance:verify:signatures",
      "id": "ci:signed-identity",
      "kind": "github-actions-job",
      "locator": ".github/workflows/governance.yml#jobs.validate",
      "subject": "github-verified-commit-identity"
    },
    {
      "enforcementCapable": false,
      "expectedCommand": null,
      "id": "github:independent-review",
      "kind": "github-ruleset",
      "locator": "github://OverlayKit/overlaykit/rulesets/main",
      "subject": "pull-request-review"
    },
    {
      "enforcementCapable": false,
      "expectedCommand": null,
      "id": "github:signed-commits",
      "kind": "github-ruleset",
      "locator": "github://OverlayKit/overlaykit/rulesets/main",
      "subject": "commit-authenticity"
    },
    {
      "enforcementCapable": false,
      "expectedCommand": "npm run ruleset:apply --workspace @overlaykit/governance-host --",
      "id": "repo:github-ruleset-controller",
      "kind": "local-command",
      "locator": "package.json#scripts.governance:ruleset:apply",
      "subject": "github-ruleset-activation"
    },
    {
      "enforcementCapable": true,
      "expectedCommand": "npm run compile --workspace @overlaykit/governance-host",
      "id": "repo:governance-compiler",
      "kind": "local-command",
      "locator": "package.json#scripts.governance:compile",
      "subject": "governance-plan"
    }
  ],
  "mechanismsHash": "9c3da015cdacfbb012a076420bfe1eb62e81b533eb6d853e1f557d70c070a671",
  "planHash": "b00acc4b819206029e1ecb7670faa847f9fc2c0b0d46a67ff92ab11f130e9b62",
  "profileHash": "b77d68c891f4ff6bd2a4d5d51cde61d2efb6457eae01888119fd1dc8c8a51fc3",
  "profileName": "overlaykit-oss",
  "profileVersion": "2.24.0",
  "rules": [
    {
      "id": "accepted-decisions-are-immutable",
      "kind": "rule",
      "sourceDecision": "ADR-0003",
      "statement": "An accepted decision is never edited or deleted; a successor decision derives supersession."
    },
    {
      "id": "accepted-specifications-are-immutable",
      "kind": "rule",
      "sourceDecision": "ADR-0003",
      "statement": "An accepted product specification is never edited or deleted; a successor specification derives supersession."
    },
    {
      "id": "action-catalog-claims-are-bounded",
      "kind": "rule",
      "sourceDecision": "ADR-0015",
      "statement": "Passing pure projection tests may not be presented as HTTP publication, server inventory authority, saved-Scene discovery, Take, value, trigger or cue support, feedback, Studio parity, Companion integration, hardware behavior, or execution authorization."
    },
    {
      "id": "action-catalog-inventory-fails-closed",
      "kind": "rule",
      "sourceDecision": "ADR-0015",
      "statement": "The complete action inventory must be bounded, supported, canonical, and unique before projection; malformed inventory cannot yield a partial catalog."
    },
    {
      "id": "action-catalog-is-not-authority",
      "kind": "rule",
      "sourceDecision": "ADR-0015",
      "statement": "A catalog descriptor may describe an action but must never grant command execution; every command still requires fresh authorization at its execution boundary."
    },
    {
      "id": "action-catalog-omits-authority-and-state",
      "kind": "rule",
      "sourceDecision": "ADR-0015",
      "statement": "Catalog descriptors must omit bearer and credential material, interactive identity, granted scope lists, production revisions, and assertions of current state."
    },
    {
      "id": "action-catalog-output-is-canonical",
      "kind": "rule",
      "sourceDecision": "ADR-0015",
      "statement": "Equivalent inventory and authority must produce byte-equivalent catalog output using fixed semantic ranks and locale-independent text ordering without mutating inputs."
    },
    {
      "id": "action-catalog-requires-capability-authority-intersection",
      "kind": "rule",
      "sourceDecision": "ADR-0015",
      "statement": "An action may be projected only when its Show, required scope, exact Preview or Program target, canonical control identifier, and explicit inventory capability all intersect."
    },
    {
      "id": "agents-are-delegated",
      "kind": "rule",
      "sourceDecision": "ADR-0003",
      "statement": "An agent identity has no independent project authority and must name its human principal."
    },
    {
      "id": "changes-reference-specifications",
      "kind": "rule",
      "sourceDecision": "ADR-0003",
      "statement": "Version-two architecture, product, security, and documentation changes reference the specifications whose observable criteria authorize their scope."
    },
    {
      "id": "claims-are-typed",
      "kind": "rule",
      "sourceDecision": "ADR-0003",
      "statement": "Every change separates facts, inferences, assumptions, and unknowns; facts and inferences require evidence."
    },
    {
      "id": "credentials-are-purpose-scoped",
      "kind": "rule",
      "sourceDecision": "ADR-0004",
      "statement": "Studio sessions, OBS output tokens, and device tokens are separate, revocable credentials with least-privilege scopes."
    },
    {
      "id": "cue-content-is-operation-bound",
      "kind": "rule",
      "sourceDecision": "ADR-0006",
      "statement": "One cue operation identifier is idempotent only for identical cue content and expected initial revision."
    },
    {
      "id": "cue-execution-is-ordered-fail-fast",
      "kind": "rule",
      "sourceDecision": "ADR-0006",
      "statement": "Cue steps execute in declared order and execution stops at the first failed step."
    },
    {
      "id": "cue-has-one-target",
      "kind": "rule",
      "sourceDecision": "ADR-0006",
      "statement": "A cue names one Show and one Preview or Program target that applies to every contained intent."
    },
    {
      "id": "cue-preserves-intent-authority",
      "kind": "rule",
      "sourceDecision": "ADR-0006",
      "statement": "Every cue preserves ADR-0005 target revision checks, direct Program authorization, runtime-only mutation, and honest receipt scope."
    },
    {
      "id": "cue-unifies-one-and-many",
      "kind": "rule",
      "sourceDecision": "ADR-0006",
      "statement": "One production action is a one-step cue and sequential coordinated work uses the same cue contract with additional ordered steps."
    },
    {
      "id": "device-action-authorization-is-fresh",
      "kind": "rule",
      "sourceDecision": "ADR-0014",
      "statement": "Every device action must resolve and authorize the bearer against the exact route-derived authority before Show lookup or production mutation so rotation, expiration, revocation, and scope changes fail closed on the next request."
    },
    {
      "id": "device-admission-rechecks-authority-at-slot-installation",
      "kind": "rule",
      "sourceDecision": "ADR-0026",
      "statement": "The coordinator must recheck the monitor currency witness before queueing, within the serialized credential lane, and immediately before installing the exclusive connection slot."
    },
    {
      "id": "device-audit-evidence-is-privacy-bounded",
      "kind": "rule",
      "sourceDecision": "ADR-0028",
      "statement": "Transition evidence may persist bounded identifiers, hashes, generations, targets, revisions, signer identifiers, reasons, and times but must never persist raw or sealed bearers, scopes, labels, control definitions, editorial content, or complete snapshot bytes."
    },
    {
      "id": "device-audit-witness-is-never-operation-authority",
      "kind": "rule",
      "sourceDecision": "ADR-0028",
      "statement": "A ledger sequence, hash, record, or readiness witness must never authorize admission, reconnection, a command, or production mutation and must not be exposed by the public ready notification."
    },
    {
      "id": "device-authority-barrier-blocks-before-drain",
      "kind": "rule",
      "sourceDecision": "ADR-0021",
      "statement": "Replacement, rotation, revocation, expiration and Show archival must deny later operation admission before waiting for begun work and transport closure."
    },
    {
      "id": "device-authority-barrier-success-requires-quiescence",
      "kind": "rule",
      "sourceDecision": "ADR-0021",
      "statement": "A lifecycle barrier may report success only after every affected begun operation settles and every affected transport closes successfully."
    },
    {
      "id": "device-authority-evidence-has-ten-second-hard-staleness",
      "kind": "rule",
      "sourceDecision": "ADR-0026",
      "statement": "A device connection must fail closed when its last positive authoritative observation reaches ten seconds or when source, resolver, clock, notification, or scheduler evidence becomes unavailable."
    },
    {
      "id": "device-authority-expiration-fails-closed",
      "kind": "rule",
      "sourceDecision": "ADR-0021",
      "statement": "Expiration must schedule a close-and-drain barrier without traffic, and inability to schedule that deadline must prevent connection admission."
    },
    {
      "id": "device-authority-invalidation-is-irreversible",
      "kind": "rule",
      "sourceDecision": "ADR-0026",
      "statement": "After host detection of changed, expired, or unavailable authority, the old connection may never regain operation authority; restoration requires a new authenticated connection."
    },
    {
      "id": "device-authority-is-exact",
      "kind": "rule",
      "sourceDecision": "ADR-0009",
      "statement": "Device authorization requires the credential's exact Show, declared scope, allowed Preview or Program target, and allowed control identifier."
    },
    {
      "id": "device-authority-is-freshly-resolved",
      "kind": "rule",
      "sourceDecision": "ADR-0009",
      "statement": "Every device action and feedback-authority projection resolves the presented bearer against current expiration, revocation, generation, and sealed-secret state before admission."
    },
    {
      "id": "device-authority-monitor-subscribes-before-reread",
      "kind": "rule",
      "sourceDecision": "ADR-0026",
      "statement": "Before upgrade authority can be granted, the host must arm authority observation before rereading current effective authority and must reject or invalidate every change observed across that race."
    },
    {
      "id": "device-authority-notifications-do-not-renew-freshness",
      "kind": "rule",
      "sourceDecision": "ADR-0026",
      "statement": "An authority notification, including one with the admitted hash, may trigger revalidation but cannot renew the positive-evidence timestamp without an authoritative reread."
    },
    {
      "id": "device-authority-precedes-network-listen",
      "kind": "rule",
      "sourceDecision": "ADR-0013",
      "statement": "Production REST and WebSocket listeners may be created only after protocol loading, device credential store initialization, and lifecycle composition succeed."
    },
    {
      "id": "device-authority-retirement-blocks-new-work-and-bounds-transport",
      "kind": "rule",
      "sourceDecision": "ADR-0026",
      "statement": "Invalidation must quiesce the exact lease immediately, reject queued and new operations, permit only already-admitted operations to settle, and close or forcibly terminate transport within twelve seconds."
    },
    {
      "id": "device-bearer-disclosure-is-bounded",
      "kind": "rule",
      "sourceDecision": "ADR-0013",
      "statement": "Only successful issue and rotate responses may disclose a device bearer, those responses must be non-cacheable, API responses must omit sealedSecret, and persistence must omit bearer plaintext."
    },
    {
      "id": "device-bearer-is-one-time",
      "kind": "rule",
      "sourceDecision": "ADR-0009",
      "statement": "Issuance and rotation return an opaque bearer once while credential storage receives only its sealed representation."
    },
    {
      "id": "device-bearer-transport-is-singular",
      "kind": "rule",
      "sourceDecision": "ADR-0014",
      "statement": "Device control accepts exactly one Bearer credential from Authorization and must reject credential transport through query parameters, request bodies, cookies, or duplicate Authorization fields."
    },
    {
      "id": "device-bootstrap-ack-is-strict-and-target-bound",
      "kind": "rule",
      "sourceDecision": "ADR-0023",
      "statement": "A bootstrap acknowledgement must use the supported version and type, an authorized explicit Preview or Program target, canonical lowercase SHA-256, exactly one applied or bounded error outcome, and no extra or free-text fields; its target-hash pair must have been issued on that connection."
    },
    {
      "id": "device-bootstrap-claims-are-bounded",
      "kind": "rule",
      "sourceDecision": "ADR-0023",
      "statement": "Passing coordinator evidence may not be represented as production mounting, real frame construction or signing, durable sequence reservation, certified network delivery, command or delta authority, close-code or backpressure policy, renderer or OBS observation, Companion integration, physical hardware application, or operator perception."
    },
    {
      "id": "device-bootstrap-deadline-is-authority-relative",
      "kind": "rule",
      "sourceDecision": "ADR-0023",
      "statement": "One absolute twelve-second bootstrap deadline starts only after exclusive connection authority is granted and cannot be reset by target changes, retries, acknowledgements, or adapter delay."
    },
    {
      "id": "device-bootstrap-emission-is-globally-ordered",
      "kind": "rule",
      "sourceDecision": "ADR-0023",
      "statement": "All target snapshot attempts on one connection must use one serialized emission lane and strictly increasing positive global issuer-audience sequences; retries must capture current truth into fresh bytes and sequence."
    },
    {
      "id": "device-bootstrap-empty-target-is-complete",
      "kind": "rule",
      "sourceDecision": "ADR-0025",
      "statement": "An authorized target with no current scene or components must be represented as a valid complete revision-zero snapshot and may satisfy readiness through the ordinary current applied acknowledgement."
    },
    {
      "id": "device-bootstrap-freshness-is-checked-at-every-authority-boundary",
      "kind": "rule",
      "sourceDecision": "ADR-0025",
      "statement": "Snapshot currency must be checked synchronously immediately before transport, during acknowledgement admission, and before readiness grant against target revision, current durable catalog generation, immutable signer, and the three-second capture-age limit."
    },
    {
      "id": "device-bootstrap-invalidation-follows-authority-scope",
      "kind": "rule",
      "sourceDecision": "ADR-0025",
      "statement": "A target revision change invalidates only that target without consuming a retry, while a shared catalog or signing-key change invalidates all affected target evidence and requires fresh issuance."
    },
    {
      "id": "device-bootstrap-issuance-uses-one-production-cut",
      "kind": "rule",
      "sourceDecision": "ADR-0025",
      "statement": "One issuance attempt must read ProductionState exactly once and derive its complete target snapshot and effective authorized catalog observation from that same cut."
    },
    {
      "id": "device-bootstrap-issuer-claims-are-bounded",
      "kind": "rule",
      "sourceDecision": "ADR-0025",
      "statement": "Passing issuer evidence may not be represented as production mounting, proof that all mutations are observed, automatic orphan-marker recovery, signing-key distribution or certification, permission-change lifecycle closure, certified network delivery, command or delta authority, Companion integration, renderer or OBS observation, physical device state, or operator perception."
    },
    {
      "id": "device-bootstrap-protocol-and-internal-failures-close",
      "kind": "rule",
      "sourceDecision": "ADR-0023",
      "statement": "Malformed, unauthorized, never-issued, or cross-target acknowledgements and invalid sequence, snapshot, hash, capture, construction, signing, hashing, or scheduling behavior must close fail-closed without granting readiness; only issued non-current pairs and exact duplicate current applied acknowledgements may be ignored."
    },
    {
      "id": "device-bootstrap-readiness-is-target-complete",
      "kind": "rule",
      "sourceDecision": "ADR-0023",
      "statement": "A connection may become ready only after every credential-authorized target has both successful transport-send completion and an applied acknowledgement for its current snapshot hash."
    },
    {
      "id": "device-bootstrap-reissue-follows-causal-scope",
      "kind": "rule",
      "sourceDecision": "ADR-0028",
      "statement": "A committed target-local production revision must invalidate and reissue only that target, while a shared catalog generation change must invalidate and reissue every authorized target without consuming delivery retries."
    },
    {
      "id": "device-bootstrap-retries-are-target-local-and-bounded",
      "kind": "rule",
      "sourceDecision": "ADR-0023",
      "statement": "Each target permits one initial attempt plus three retries shared equally by send failure, a three-second post-send acknowledgement timeout, and current bounded error acknowledgement; exhaustion by any target closes the whole connection."
    },
    {
      "id": "device-bootstrap-sequence-precedes-signature-and-is-consumed",
      "kind": "rule",
      "sourceDecision": "ADR-0025",
      "statement": "After current catalog persistence, issuance must reserve from the shared durable issuer-audience sequence lane before payload construction and signing, and every returned sequence remains consumed after any later outcome."
    },
    {
      "id": "device-bootstrap-state-change-invalidates-only-its-target",
      "kind": "rule",
      "sourceDecision": "ADR-0023",
      "statement": "A target state change must invalidate that target's pending or applied pair, preserve its accumulated retries, retain other targets' evidence, coalesce intermediate changes, and schedule latest truth without charging a retry."
    },
    {
      "id": "device-bootstrap-v2-signs-exact-canonical-payload",
      "kind": "rule",
      "sourceDecision": "ADR-0025",
      "statement": "A device bootstrap frame must use version two, carry a positive catalog generation inside canonical payload bytes, and admit only a detached signature over those exact immutable bytes."
    },
    {
      "id": "device-catalog-adapter-is-bounded-and-fails-closed",
      "kind": "rule",
      "sourceDecision": "ADR-0016",
      "statement": "The inventory adapter must stop before exceeding 1,000 aggregate capabilities, bound labels to protocol limits, and allow duplicate target-control identities to fail the complete pure projection rather than silently choosing one."
    },
    {
      "id": "device-catalog-authenticates-fresh-authority",
      "kind": "rule",
      "sourceDecision": "ADR-0016",
      "statement": "Every device catalog request must freshly authenticate exactly one bearer and must not accept cookies, query authority, duplicate Authorization fields, or a Studio session as device authority."
    },
    {
      "id": "device-catalog-binds-active-route-show",
      "kind": "rule",
      "sourceDecision": "ADR-0016",
      "statement": "The authenticated device authority must name the exact route-derived Show, and inventory may be read only after that Show is confirmed to exist and remain active."
    },
    {
      "id": "device-catalog-command-authority-remains-separate",
      "kind": "rule",
      "sourceDecision": "ADR-0016",
      "statement": "Selecting a catalog entry never bypasses fresh command authorization, active-Show checks, expected revision, idempotency, or domain validation at execution time."
    },
    {
      "id": "device-catalog-esm-runtime-is-composed-asynchronously",
      "kind": "rule",
      "sourceDecision": "ADR-0016",
      "statement": "A CommonJS server must load the ESM catalog projector through native asynchronous import behind an injected port and must verify the compiled runtime rather than synchronously requiring the ESM package."
    },
    {
      "id": "device-catalog-generation-failure-is-audience-local",
      "kind": "rule",
      "sourceDecision": "ADR-0025",
      "statement": "Unexpected catalog persistence uncertainty must block the affected audience without lowering its guarantee or reusing an old generation, while recovery may occur only after the current pending generation is successfully persisted."
    },
    {
      "id": "device-catalog-generation-is-durable-and-audience-wide",
      "kind": "rule",
      "sourceDecision": "ADR-0025",
      "statement": "One full audience credential shares a positive catalog generation across Preview and Program; every effective catalog change including ABA invalidates prior generations immediately and emission remains blocked until the current generation is durably committed."
    },
    {
      "id": "device-catalog-http-claims-are-bounded",
      "kind": "rule",
      "sourceDecision": "ADR-0016",
      "statement": "Passing this HTTP slice may not be presented as feedback delivery, expected-revision delivery, catalog version coherence, distributed atomicity, saved-Scene discovery, Take, value, trigger or cue support, Studio parity, Companion integration, or hardware behavior."
    },
    {
      "id": "device-catalog-inventory-reflects-loaded-snapshots",
      "kind": "rule",
      "sourceDecision": "ADR-0016",
      "statement": "Visibility inventory is derived from immutable copies of currently loaded Preview and Program element trees, including nested components and excluding unloaded targets."
    },
    {
      "id": "device-catalog-is-point-in-time-no-store",
      "kind": "rule",
      "sourceDecision": "ADR-0016",
      "statement": "HTTP catalog responses must be marked no-store and must not include current value, production revision, credential material, or any claim that a descriptor authorizes future execution."
    },
    {
      "id": "device-connection-authority-identity-is-immutable",
      "kind": "rule",
      "sourceDecision": "ADR-0021",
      "statement": "A connection lease must capture immutable credential, generation audience, Show and expiration identity; a credential cannot change Show and one audience cannot change expiration."
    },
    {
      "id": "device-connection-authority-is-canonical-and-secret-free",
      "kind": "rule",
      "sourceDecision": "ADR-0026",
      "statement": "A connection authority identity must be SHA-256 over the exact canonical effective-authority payload and must exclude the bearer, sealed verifier, label, and administrative timestamps."
    },
    {
      "id": "device-connection-authority-is-exclusive",
      "kind": "rule",
      "sourceDecision": "ADR-0021",
      "statement": "At most one exact lease for a credential may admit work, and a replacement may become effective only after the prior transport closes and its begun operations drain."
    },
    {
      "id": "device-connection-close-reason-is-not-control-truth",
      "kind": "rule",
      "sourceDecision": "ADR-0021",
      "statement": "A transport close reason is diagnostic lifecycle metadata and may not establish an individual control value or availability state."
    },
    {
      "id": "device-connection-coordinator-claims-are-bounded",
      "kind": "rule",
      "sourceDecision": "ADR-0021",
      "statement": "Passing coordinator evidence may not be represented as WebSocket authentication or delivery, lifecycle-route integration, command execution, signed-frame delivery, close-code behavior, multi-instance coordination, cancellation of begun work, crash recovery, Companion integration, renderer or OBS observation, or hardware behavior."
    },
    {
      "id": "device-continuous-authority-claims-are-bounded",
      "kind": "rule",
      "sourceDecision": "ADR-0026",
      "statement": "Passing monitor evidence may not be represented as a production-mounted authority source, guaranteed cross-process notification delivery, physical network timing, internal operation cancellation, command or delta authority, Caddy or TLS verification, device hardware state, renderer or OBS observation, or operator perception."
    },
    {
      "id": "device-control-addition-requires-initial-state",
      "kind": "rule",
      "sourceDecision": "ADR-0020",
      "statement": "A new or replaced action descriptor may become available only when its initial authoritative observation is carried in the same atomic frame."
    },
    {
      "id": "device-control-bootstrap-is-complete",
      "kind": "rule",
      "sourceDecision": "ADR-0020",
      "statement": "The first frame must be bootstrap and must contain the complete bounded target catalog, no removals, and exactly one authoritative initial observation for every included action."
    },
    {
      "id": "device-control-catalog-hash-is-deterministic",
      "kind": "rule",
      "sourceDecision": "ADR-0020",
      "statement": "Each frame must bind lowercase SHA-256 over the versioned code-unit-ordered canonical bytes of its exact resulting Show and target catalog."
    },
    {
      "id": "device-control-claims-are-bounded",
      "kind": "rule",
      "sourceDecision": "ADR-0014",
      "statement": "Passing local device HTTP tests may not be presented as proof of network delivery, renderer or OBS application, device feedback, catalogs, cues, Take, value mutation, Companion or hardware support, device-specific rate limits, audit retention, multi-process coordination, or in-flight revocation or Show-archival linearizability."
    },
    {
      "id": "device-control-delta-builder-observes-complete-truth",
      "kind": "rule",
      "sourceDecision": "ADR-0020",
      "statement": "A delta builder must receive the complete current authorized target catalog and observations even though it emits only additions, replacements, removals, and changed values."
    },
    {
      "id": "device-control-frame-claims-are-bounded",
      "kind": "rule",
      "sourceDecision": "ADR-0020",
      "statement": "Passing frame-protocol evidence may not be represented as WebSocket authentication or delivery, commands, timers, three-second scheduling, connected or disconnected projection, operation error delivery, backpressure, reconnect implementation, server integration, key lifecycle, Companion integration, renderer or OBS observation, or hardware behavior."
    },
    {
      "id": "device-control-frame-is-canonical-and-signed",
      "kind": "rule",
      "sourceDecision": "ADR-0020",
      "statement": "Every admitted device control frame must bind its normalized complete payload to a pinned issuer, credential-generation audience, positive monotonic sequence, and verified signature."
    },
    {
      "id": "device-control-frame-reduction-is-atomic",
      "kind": "rule",
      "sourceDecision": "ADR-0020",
      "statement": "Frame reduction must validate prior state, revision, confirmation time, transition completeness and resulting catalog hash before returning any new state."
    },
    {
      "id": "device-control-lease-is-authoritative-evidence",
      "kind": "rule",
      "sourceDecision": "ADR-0020",
      "statement": "Only a signed catalog-bound server confirmation may renew unchanged active or inactive controls; a transport acknowledgement may not renew their truth."
    },
    {
      "id": "device-control-preserves-production-concurrency",
      "kind": "rule",
      "sourceDecision": "ADR-0014",
      "statement": "Device visibility execution must preserve ProductionService expected-revision, operation-id replay, operation-id conflict, Preview isolation, and bounded server-state receipt semantics."
    },
    {
      "id": "device-control-principal-is-separated",
      "kind": "rule",
      "sourceDecision": "ADR-0014",
      "statement": "A device Control API request must resolve only device authority and must never authenticate, construct, or inherit a Studio session principal."
    },
    {
      "id": "device-control-removal-is-unavailable",
      "kind": "rule",
      "sourceDecision": "ADR-0020",
      "statement": "A control removed from the resulting authorized catalog must become unavailable atomically rather than unknown, disconnected, or failed."
    },
    {
      "id": "device-credential-authority-is-exclusive-sqlite",
      "kind": "rule",
      "sourceDecision": "ADR-0027",
      "statement": "A self-hosted OverlayKit server must hold one long-lived exclusive Node 24 SQLite connection as the only executable credential authority and must not expose device control when that ownership cannot be acquired."
    },
    {
      "id": "device-credential-commit-precedes-owner-success",
      "kind": "rule",
      "sourceDecision": "ADR-0027",
      "statement": "Issue, rotation, revocation, and effective expiration must publish immutable post-commit authority or null to current affected listeners before the corresponding Owner mutation may report success."
    },
    {
      "id": "device-credential-legacy-json-is-migration-input-only",
      "kind": "rule",
      "sourceDecision": "ADR-0027",
      "statement": "Legacy credential JSON may be parsed and imported only as one complete transactional migration whose exact committed input is recorded before archival; it may never remain a parallel executable authority."
    },
    {
      "id": "device-credential-listener-failure-is-audience-local",
      "kind": "rule",
      "sourceDecision": "ADR-0027",
      "statement": "A post-commit listener failure cannot roll back persisted truth and must fail only that credential audience closed by offering null to all of its current listeners."
    },
    {
      "id": "device-credential-permission-change-rotates-atomically",
      "kind": "rule",
      "sourceDecision": "ADR-0027",
      "statement": "Every successful permission change must atomically persist a new complete authority generation and bearer, making the prior token invalid at the transaction commit boundary."
    },
    {
      "id": "device-credential-sqlite-mutations-use-generation-cas",
      "kind": "rule",
      "sourceDecision": "ADR-0027",
      "statement": "Credential create and replacement must commit transactionally, and replacement may succeed only when the persisted generation equals the caller's expected generation."
    },
    {
      "id": "device-credential-sqlite-never-stores-bearer",
      "kind": "rule",
      "sourceDecision": "ADR-0027",
      "statement": "SQLite credential authority may persist only validated sealed secret material and must never persist a raw OverlayKit device bearer."
    },
    {
      "id": "device-credential-sqlite-state-validates-before-use",
      "kind": "rule",
      "sourceDecision": "ADR-0027",
      "statement": "Every SQLite credential row and structured authority field must satisfy the complete credential lifecycle contract before the record is exposed or mutated; malformed persisted authority fails closed."
    },
    {
      "id": "device-crypto-claims-are-bounded",
      "kind": "rule",
      "sourceDecision": "ADR-0011",
      "statement": "Passing adapter tests may not be presented as primitive certification, memory or host compromise resistance, transport security, bearer recovery, replay prevention, rate limiting, endpoint integration, or hardware support."
    },
    {
      "id": "device-crypto-failures-fail-closed",
      "kind": "rule",
      "sourceDecision": "ADR-0011",
      "statement": "Entropy or sealing failure prevents credential persistence, and verifier parsing, digest, or comparison failure denies authentication."
    },
    {
      "id": "device-direct-program-is-external-capability",
      "kind": "rule",
      "sourceDecision": "ADR-0014",
      "statement": "ProductionService may receive direct Program authorization from the device route only after the same request bearer has been freshly authorized for the exact Program target and control."
    },
    {
      "id": "device-feedback-authority-is-captured-once",
      "kind": "rule",
      "sourceDecision": "ADR-0019",
      "statement": "The validated request, credential-generation audience, credential authority, and issuer key identifier must be captured once and must not be reread from mutable collaborators after an asynchronous boundary."
    },
    {
      "id": "device-feedback-derives-from-current-server-truth",
      "kind": "rule",
      "sourceDecision": "ADR-0019",
      "statement": "Visibility feedback subjects must come only from the current authorized action catalog and observations must come only from one committed ProductionSnapshot for the exact target."
    },
    {
      "id": "device-feedback-issuer-initializes-before-exposure",
      "kind": "rule",
      "sourceDecision": "ADR-0019",
      "statement": "A device feedback issuer may be exposed to an adapter only after its sequence store and required public protocol ports initialize successfully with an externally supplied signer."
    },
    {
      "id": "device-feedback-reauthenticates-exact-authority",
      "kind": "rule",
      "sourceDecision": "ADR-0019",
      "statement": "Every feedback issuance must freshly authenticate the device credential and require feedback-read authority for the exact Show and production target before projection, reservation, or signing."
    },
    {
      "id": "device-feedback-reserved-sequences-are-never-reused",
      "kind": "rule",
      "sourceDecision": "ADR-0019",
      "statement": "After a sequence reservation succeeds, signing failure may create a gap but no reserved sequence may be reused."
    },
    {
      "id": "device-feedback-return-is-atomic",
      "kind": "rule",
      "sourceDecision": "ADR-0019",
      "statement": "One issuance must return the complete canonically signed ordered projection or no batch; projection, reservation, or signing failure must never return a partial batch."
    },
    {
      "id": "device-feedback-sequences-precede-signing",
      "kind": "rule",
      "sourceDecision": "ADR-0019",
      "statement": "An exact contiguous sequence batch must be persisted by immutable issuer key identifier and credential-generation audience before signing begins."
    },
    {
      "id": "device-feedback-single-instance-claims-are-bounded",
      "kind": "rule",
      "sourceDecision": "ADR-0019",
      "statement": "Passing issuer and file-store evidence may not be represented as key lifecycle, multi-process coordination, directory-fsync power-loss durability, network delivery, three-second scheduling, acknowledgement, reconnect recovery, renderer or OBS observation, Companion integration, or hardware state."
    },
    {
      "id": "device-lifecycle-authority-is-external",
      "kind": "rule",
      "sourceDecision": "ADR-0009",
      "statement": "Credential lifecycle accepts Owner identity, clock, entropy, secret sealing, and storage authority only from trusted adapters outside the bearer credential."
    },
    {
      "id": "device-lifecycle-http-is-owner-only",
      "kind": "rule",
      "sourceDecision": "ADR-0013",
      "statement": "Device credential issue, rotate, and revoke operations require an authenticated Owner session and the interactive browser-origin boundary."
    },
    {
      "id": "device-lifecycle-http-is-show-bound",
      "kind": "rule",
      "sourceDecision": "ADR-0013",
      "statement": "Issue authority comes from an existing active Show route, and rotate or revoke must reject a stored credential that does not belong to the active Show named by that route."
    },
    {
      "id": "device-operation-authority-begins-at-execution",
      "kind": "rule",
      "sourceDecision": "ADR-0021",
      "statement": "Receiving or queueing an instruction grants no authority; an operation may begin only after its current exact lease is synchronously admitted at the execution boundary."
    },
    {
      "id": "device-principal-is-not-studio",
      "kind": "rule",
      "sourceDecision": "ADR-0009",
      "statement": "A valid device bearer resolves to device authority and never to a Studio user, role set, cookie, or interactive session."
    },
    {
      "id": "device-readiness-is-commit-before-effect",
      "kind": "rule",
      "sourceDecision": "ADR-0028",
      "statement": "A device connection may become ready only after current authority and complete exact-target bootstrap evidence are synchronously validated and durably appended; readiness projection and notification must follow that commit."
    },
    {
      "id": "device-rotation-changes-feedback-audience",
      "kind": "rule",
      "sourceDecision": "ADR-0009",
      "statement": "Rotation preserves credential identity, replaces its secret, increments generation, and binds feedback audience to credentialId.generation so prior generations fail closed."
    },
    {
      "id": "device-safety-transitions-are-effect-before-audit",
      "kind": "rule",
      "sourceDecision": "ADR-0028",
      "statement": "Quiescing and closure must remove device authority before their audit append, and append uncertainty must close device admission and transports and terminate the host rather than restore or retain authority."
    },
    {
      "id": "device-secret-has-256-random-bits",
      "kind": "rule",
      "sourceDecision": "ADR-0011",
      "statement": "A production device secret must be generated from exactly 32 bytes returned by the approved cryptographic random source and encoded as canonical unpadded base64url."
    },
    {
      "id": "device-sequence-authority-is-exclusive-per-canonical-store",
      "kind": "rule",
      "sourceDecision": "ADR-0024",
      "statement": "A cooperating server sequence store must acquire one exclusive ownership marker for the canonical document path before loading or reserving, and a second live authority for that path must fail closed."
    },
    {
      "id": "device-sequence-claims-are-bounded",
      "kind": "rule",
      "sourceDecision": "ADR-0024",
      "statement": "Passing file-store evidence may not be represented as physical-media proof, protection from non-cooperating writers, distributed authority, automatic orphan recovery, mounted operator health visibility, real frame construction or signing, WebSocket delivery, renderer or OBS observation, Companion integration, or hardware state."
    },
    {
      "id": "device-sequence-close-is-a-barrier",
      "kind": "rule",
      "sourceDecision": "ADR-0024",
      "statement": "Explicit close must reject newly requested reservations, drain reservations accepted before close, verify marker ownership, and remove only the closing authority's marker."
    },
    {
      "id": "device-sequence-commit-precedes-exposure",
      "kind": "rule",
      "sourceDecision": "ADR-0024",
      "statement": "No reserved sequence may be returned, signed, or exposed to transport before the complete next document is written to a private temporary file, file-synchronized, atomically replaced, and directory-synchronized when supported."
    },
    {
      "id": "device-sequence-degradation-is-narrow",
      "kind": "rule",
      "sourceDecision": "ADR-0024",
      "statement": "Only a directory synchronization operation specifically reported unsupported may lower the guarantee and continue; malformed state, exhaustion, ownership conflict, file synchronization, replacement, unexpected directory synchronization, permission, and other I/O failures must fail closed without returning a reservation."
    },
    {
      "id": "device-sequence-durability-is-observable",
      "kind": "rule",
      "sourceDecision": "ADR-0024",
      "statement": "The sequence authority must report power_loss_resilient only while directory synchronization succeeds and must report process_restart_resilient whenever unsupported directory synchronization forces automatic degradation."
    },
    {
      "id": "device-sequence-lane-is-global-per-issuer-audience",
      "kind": "rule",
      "sourceDecision": "ADR-0024",
      "statement": "All device message producers using one authority must reserve from the same monotonically increasing lane keyed only by immutable issuer key and credential-generation audience; targets and message kinds may not create independent counters."
    },
    {
      "id": "device-sequence-reservations-are-never-reused",
      "kind": "rule",
      "sourceDecision": "ADR-0024",
      "statement": "Every successfully returned sequence remains consumed forever even when later frame construction, signing, sending, or acknowledgement fails."
    },
    {
      "id": "device-server-composition-claims-are-bounded",
      "kind": "rule",
      "sourceDecision": "ADR-0013",
      "statement": "Passing bootstrap and Owner HTTP tests may not be presented as credential listing, response-loss recovery, concurrent archival linearizability, device request authentication, command or feedback transport, UI or Companion integration, registry provenance, multi-process coordination, in-flight revocation, rate-limit policy, audit logging, or hardware support."
    },
    {
      "id": "device-shutdown-closes-admission-before-drain",
      "kind": "rule",
      "sourceDecision": "ADR-0027",
      "statement": "Server shutdown must synchronously stop new upgrades and device admission before retiring authority, draining only admitted operations, closing credential storage, and forcibly terminating remaining transports within twelve seconds."
    },
    {
      "id": "device-sqlite-authority-claims-are-bounded",
      "kind": "rule",
      "sourceDecision": "ADR-0027",
      "statement": "Passing SQLite authority evidence may not be represented as abrupt-power or physical-media durability, network-filesystem coordination, hostile database access prevention, cross-process listener delivery, proxy or TLS verification, bootstrap or command authority, Companion integration, hardware state, renderer or OBS observation, or operator perception."
    },
    {
      "id": "device-transition-audit-claims-are-bounded",
      "kind": "rule",
      "sourceDecision": "ADR-0028",
      "statement": "Passing transition-ledger and bootstrap evidence may not be represented as cryptographic audit signing, audit-key lifecycle, hostile out-of-band database resistance, abrupt-power or physical-media durability, archive or retention verification, bootstrap-key custody, command or delta execution, macro support, proxy or TLS verification, Companion integration, hardware state, renderer or OBS observation, or operator perception."
    },
    {
      "id": "device-transition-history-validates-before-host-epoch",
      "kind": "rule",
      "sourceDecision": "ADR-0028",
      "statement": "The complete canonical transition history and its separately committed durable head must validate before a runtime may append a new host epoch or expose audited device readiness."
    },
    {
      "id": "device-transition-ledger-shares-credential-sqlite-authority",
      "kind": "rule",
      "sourceDecision": "ADR-0028",
      "statement": "The device transition ledger must use the same long-lived exclusive SQLite connection as credential authority and must never open or project a second executable authority."
    },
    {
      "id": "device-transition-records-form-dual-hash-chain",
      "kind": "rule",
      "sourceDecision": "ADR-0028",
      "statement": "Every transition record must have one positive global sequence, the exact previous global hash, the exact previous connection hash when connection-scoped, bounded canonical evidence, and a SHA-256 record identity."
    },
    {
      "id": "device-unsealed-host-epoch-becomes-discontinuity",
      "kind": "rule",
      "sourceDecision": "ADR-0028",
      "statement": "After verifying an unsealed prior host epoch, the next successful startup must append an explicit discontinuity and close every surviving connection chain without restoring prior authority."
    },
    {
      "id": "device-verifier-is-not-a-password-verifier",
      "kind": "rule",
      "sourceDecision": "ADR-0011",
      "statement": "The device verifier construction applies only to a 256-bit machine-generated secret and may not replace the approved KDF for human passwords."
    },
    {
      "id": "device-verifier-is-versioned-and-domain-separated",
      "kind": "rule",
      "sourceDecision": "ADR-0011",
      "statement": "A stored device verifier must use the accepted version and algorithm and hash the complete bearer after the device-credential domain separator."
    },
    {
      "id": "device-verifier-parses-before-comparison",
      "kind": "rule",
      "sourceDecision": "ADR-0011",
      "statement": "Authentication must reject unsupported or noncanonical verifier representations before comparing an equal-length 32-byte candidate and stored digest with the approved constant-time primitive."
    },
    {
      "id": "device-visibility-authority-is-route-derived",
      "kind": "rule",
      "sourceDecision": "ADR-0014",
      "statement": "The device visibility route must derive Show, Preview or Program target, and canonical `<componentId>.visibility` control authority from route coordinates and must fix the required scope to component.visibility:write."
    },
    {
      "id": "device-visibility-body-cannot-grant-authority",
      "kind": "rule",
      "sourceDecision": "ADR-0014",
      "statement": "A device visibility body may contain only visible, operationId, and expectedRevision and must not name or override Show, scope, target, component, control, role, or direct-Program authority."
    },
    {
      "id": "device-websocket-admission-claims-are-bounded",
      "kind": "rule",
      "sourceDecision": "ADR-0022",
      "statement": "Passing gateway evidence may not be represented as production mounting, exact credential-failure auditing, admission rate or timeout policy, TLS or proxy certification, lifecycle or natural-disconnect retirement, snapshot or acknowledgement delivery, retries, deadlines, ready command execution, deltas, close-code policy, distributed coordination, Companion integration, renderer or OBS observation, or hardware behavior."
    },
    {
      "id": "device-websocket-authenticates-before-upgrade",
      "kind": "rule",
      "sourceDecision": "ADR-0022",
      "statement": "A device request may reach handleUpgrade only after exactly one Authorization bearer authenticates into current credential authority; invalid credential outcomes must share one public 401 shape and must not reach coordinator admission."
    },
    {
      "id": "device-websocket-authority-is-credential-derived",
      "kind": "rule",
      "sourceDecision": "ADR-0022",
      "statement": "Coordinator admission may receive only immutable credential identifier, generation audience, generation, Show, and expiration authority captured from the authenticated credential, never a client-selected Show or Studio or Output identity."
    },
    {
      "id": "device-websocket-is-native-only",
      "kind": "rule",
      "sourceDecision": "ADR-0022",
      "statement": "A device WebSocket handshake must reject every Origin header and every cookie or query authority source before upgrade."
    },
    {
      "id": "device-websocket-negotiates-highest-version",
      "kind": "rule",
      "sourceDecision": "ADR-0022",
      "statement": "A device WebSocket handshake must select the highest mutually supported versioned device subprotocol and reject the request before upgrade when no supported version intersects."
    },
    {
      "id": "device-websocket-paths-have-one-owner",
      "kind": "rule",
      "sourceDecision": "ADR-0027",
      "statement": "The production WebSocket listener must route /ws only to browser and OBS transport, /device only to non-browser device transport, and reject every other path without handler fallback."
    },
    {
      "id": "device-websocket-pre-ready-work-is-rejected",
      "kind": "rule",
      "sourceDecision": "ADR-0022",
      "statement": "Every message received before later readiness evidence must be rejected as not_ready without parsing, buffering, queueing, or execution."
    },
    {
      "id": "device-websocket-transport-is-not-readiness",
      "kind": "rule",
      "sourceDecision": "ADR-0022",
      "statement": "Completing 101 establishes transport only and cannot be represented as exclusive connection authority, synchronized device state, command authority, or successful device application."
    },
    {
      "id": "done-is-observed",
      "kind": "rule",
      "sourceDecision": "ADR-0003",
      "statement": "A change is ready only when every enforced gate passed and every enforced artifact is present for the current planHash and manifestHash."
    },
    {
      "id": "evidence-cannot-redefine-law",
      "kind": "rule",
      "sourceDecision": "ADR-0003",
      "statement": "A governance run may report outcomes only for gates and bindings already present in its matching plan and manifest."
    },
    {
      "id": "feedback-authority-is-external",
      "kind": "rule",
      "sourceDecision": "ADR-0008",
      "statement": "Credential audience and feedback scopes come from externally established authority and may never be granted by fields inside the feedback envelope."
    },
    {
      "id": "feedback-envelope-is-canonical",
      "kind": "rule",
      "sourceDecision": "ADR-0008",
      "statement": "Trusted feedback signs a canonical envelope containing its schema version, issuer key, credential audience, sequence, and complete normalized event."
    },
    {
      "id": "feedback-failure-needs-later-observation",
      "kind": "rule",
      "sourceDecision": "ADR-0007",
      "statement": "An explicit operation failure remains failed until a strictly later authoritative-server observation recovers the control."
    },
    {
      "id": "feedback-issuer-is-externally-pinned",
      "kind": "rule",
      "sourceDecision": "ADR-0008",
      "statement": "Feedback admission verifies the signature against an issuer key pinned outside the received envelope."
    },
    {
      "id": "feedback-lease-fails-closed",
      "kind": "rule",
      "sourceDecision": "ADR-0007",
      "statement": "A server observation is current for less than three seconds and becomes stale with unknown button state at exactly three seconds."
    },
    {
      "id": "feedback-replay-fails-closed",
      "kind": "rule",
      "sourceDecision": "ADR-0008",
      "statement": "A feedback sequence at or below the last admitted sequence is replay and cannot reach the projector."
    },
    {
      "id": "feedback-scope-is-exact",
      "kind": "rule",
      "sourceDecision": "ADR-0008",
      "statement": "A signed event is admitted only with feedback-read scope for its exact Show, Preview or Program target, and control identifier."
    },
    {
      "id": "feedback-scope-is-server-only",
      "kind": "rule",
      "sourceDecision": "ADR-0007",
      "statement": "Control feedback reports authoritative server truth only and cannot be presented as renderer or hardware observation without separate evidence."
    },
    {
      "id": "feedback-subject-is-explicit",
      "kind": "rule",
      "sourceDecision": "ADR-0007",
      "statement": "Every control feedback projection names one Show, one Preview or Program target, and one control identifier; feedback for another subject fails closed."
    },
    {
      "id": "hardware-is-an-adapter",
      "kind": "rule",
      "sourceDecision": "ADR-0004",
      "statement": "Hardware and third-party controller support integrates through the vendor-neutral Control API and never defines the core production command model."
    },
    {
      "id": "law-is-compiled",
      "kind": "rule",
      "sourceDecision": "ADR-0003",
      "statement": "Normative governance is the compiled plan derived from accepted immutable decisions, accepted immutable specifications, and the active profile."
    },
    {
      "id": "license-is-apache-2.0",
      "kind": "rule",
      "sourceDecision": "ADR-0018",
      "statement": "OverlayKit source and public npm package distributions governed by this repository must declare SPDX Apache-2.0."
    },
    {
      "id": "license-text-is-canonical",
      "kind": "rule",
      "sourceDecision": "ADR-0018",
      "statement": "Each supported package root must carry the byte-exact official Apache License 2.0 text with SHA-256 cfc7749b96f63bd31c3c42b5c471bf756814053e847c10f3eb003417bc523d30."
    },
    {
      "id": "licensing-check-is-enforced",
      "kind": "rule",
      "sourceDecision": "ADR-0018",
      "statement": "npm run check must execute the deterministic licensing verifier and its hostile tests before the general repository quality suite."
    },
    {
      "id": "licensing-claims-are-bounded",
      "kind": "rule",
      "sourceDecision": "ADR-0018",
      "statement": "Passing licensing controls may not be presented as proof of third-party ownership, trademark rights, contributor agreements, dependency compatibility, software-bill-of-materials completeness, registry publication, historical relicensing, legal advice, or jurisdiction-specific enforceability."
    },
    {
      "id": "notice-preserves-rodrigo-attribution",
      "kind": "rule",
      "sourceDecision": "ADR-0018",
      "statement": "Each supported package root must carry the canonical NOTICE naming Rodrigo Vicente and linking @rodrigoteamx at https://x.com/rodrigoteamx."
    },
    {
      "id": "one-device-store-per-bootstrap",
      "kind": "rule",
      "sourceDecision": "ADR-0013",
      "statement": "One production bootstrap invocation must share one initialized device credential store and its lifecycle across all mounted Owner lifecycle routes."
    },
    {
      "id": "only-normalized-feedback-is-admitted",
      "kind": "rule",
      "sourceDecision": "ADR-0008",
      "statement": "Only bounded normalized fields covered by the signature may enter the trusted feedback projector; extra fields are discarded."
    },
    {
      "id": "operator-controls-are-declared",
      "kind": "rule",
      "sourceDecision": "ADR-0004",
      "statement": "A component exposes operator capabilities through typed control definitions rather than inferred variables or arbitrary implementation access."
    },
    {
      "id": "partial-execution-is-explicit",
      "kind": "rule",
      "sourceDecision": "ADR-0006",
      "statement": "A failed cue reports every completed step, the failed step and error, and the resulting revision without claiming rollback or atomicity."
    },
    {
      "id": "preview-precedes-program",
      "kind": "rule",
      "sourceDecision": "ADR-0004",
      "statement": "The default production workflow prepares Preview and promotes it to Program through an explicit Take command."
    },
    {
      "id": "production-target-is-explicit",
      "kind": "rule",
      "sourceDecision": "ADR-0005",
      "statement": "Every production intent names Preview or Program and a missing or unknown target fails closed."
    },
    {
      "id": "program-authority-is-external",
      "kind": "rule",
      "sourceDecision": "ADR-0005",
      "statement": "Direct Program authority is established by an authorization boundary and is never asserted by the intent payload itself."
    },
    {
      "id": "protocol-commonjs-uses-dynamic-import",
      "kind": "rule",
      "sourceDecision": "ADR-0012",
      "statement": "A CommonJS consumer that loads protocol runtime values must use native dynamic import; synchronous require and a separate CommonJS implementation are outside the accepted contract."
    },
    {
      "id": "protocol-exports-are-explicit-and-packed",
      "kind": "rule",
      "sourceDecision": "ADR-0012",
      "statement": "Every supported protocol entry point must declare explicit types and import targets, and every target must be present in the publication payload."
    },
    {
      "id": "protocol-package-claims-are-bounded",
      "kind": "rule",
      "sourceDecision": "ADR-0012",
      "statement": "Passing tarball-consumer tests may not be presented as registry publication, provenance, semantic-version compatibility, browser or bundler compatibility, mixed loader identity, synchronous require support, server composition, endpoint integration, or complete downstream compatibility."
    },
    {
      "id": "protocol-package-tests-use-installed-tarball",
      "kind": "rule",
      "sourceDecision": "ADR-0012",
      "statement": "Publication-boundary evidence must exercise an installed npm tarball and may not substitute direct workspace-source imports for packed-consumer behavior."
    },
    {
      "id": "protocol-publication-excludes-source-and-tests",
      "kind": "rule",
      "sourceDecision": "ADR-0012",
      "statement": "The protocol publication allowlist must expose compiled dist artifacts rather than repository source or tests."
    },
    {
      "id": "protocol-publishes-compiled-esm",
      "kind": "rule",
      "sourceDecision": "ADR-0012",
      "statement": "The public protocol runtime must be compiled from its TypeScript source as one ESM implementation accompanied by declarations."
    },
    {
      "id": "public-license-claims-are-consistent",
      "kind": "rule",
      "sourceDecision": "ADR-0018",
      "statement": "README, package documentation, contribution terms, and landing content must communicate the current Apache-2.0 license and Rodrigo Vicente attribution without a current MIT claim."
    },
    {
      "id": "public-packages-carry-legal-artifacts",
      "kind": "rule",
      "sourceDecision": "ADR-0018",
      "statement": "Every public npm package allowlist and packed payload must include LICENSE and NOTICE."
    },
    {
      "id": "receipt-scope-is-honest",
      "kind": "rule",
      "sourceDecision": "ADR-0005",
      "statement": "A server receipt reports resulting authoritative server state and cannot be presented as renderer or device observation without additional evidence."
    },
    {
      "id": "runtime-does-not-mutate-source",
      "kind": "rule",
      "sourceDecision": "ADR-0004",
      "statement": "Preview and Program state never overwrite a saved Scene or Component Definition without an explicit save-back command."
    },
    {
      "id": "runtime-intents-are-idempotent",
      "kind": "rule",
      "sourceDecision": "ADR-0005",
      "statement": "Replaying one operation identifier with the same intent does not apply twice, and reuse for another intent fails as a conflict."
    },
    {
      "id": "runtime-source-remains-immutable",
      "kind": "rule",
      "sourceDecision": "ADR-0005",
      "statement": "A production intent changes runtime state only and never overwrites saved Scene source."
    },
    {
      "id": "server-observation-establishes-feedback-truth",
      "kind": "rule",
      "sourceDecision": "ADR-0007",
      "statement": "Only a revisioned authoritative-server observation may establish current active or inactive control state."
    },
    {
      "id": "server-protocol-loader-preserves-native-import",
      "kind": "rule",
      "sourceDecision": "ADR-0013",
      "statement": "The CommonJS server must load the ESM protocol runtime through native dynamic import, and its production build must reject a rewrite of that package boundary to synchronous require."
    },
    {
      "id": "show-is-the-workspace",
      "kind": "rule",
      "sourceDecision": "ADR-0004",
      "statement": "Every saved scene, production session, output, and show-local control belongs to an explicit Show."
    },
    {
      "id": "studio-is-one-shell",
      "kind": "rule",
      "sourceDecision": "ADR-0004",
      "statement": "Authoring, production, library, security, and integrations share one authenticated Studio shell; the headless OBS output remains separate."
    },
    {
      "id": "target-revision-is-checked",
      "kind": "rule",
      "sourceDecision": "ADR-0005",
      "statement": "A production intent validates the expected revision of its named target before mutation."
    },
    {
      "id": "transport-acknowledgement-is-not-truth",
      "kind": "rule",
      "sourceDecision": "ADR-0007",
      "statement": "Transport acknowledgement is delivery metadata and may never establish, refresh, or recover production state."
    },
    {
      "id": "visibility-control-id-is-canonical",
      "kind": "rule",
      "sourceDecision": "ADR-0015",
      "statement": "A component visibility capability uses the canonical control identifier `<componentId>.visibility` in catalog and authorization subjects."
    },
    {
      "id": "visibility-feedback-binds-snapshot-subject",
      "kind": "rule",
      "sourceDecision": "ADR-0017",
      "statement": "Each projected visibility observation must bind the snapshot Show, exact Preview or Program target, canonical catalog control subject, snapshot revision, and explicit observation time."
    },
    {
      "id": "visibility-feedback-catalog-freshness-is-external",
      "kind": "rule",
      "sourceDecision": "ADR-0017",
      "statement": "A supplied action catalog selects eligible subjects but the visibility projector does not establish catalog freshness, future execution authority, or coherence with later production revisions."
    },
    {
      "id": "visibility-feedback-does-not-infer-renderer-state",
      "kind": "rule",
      "sourceDecision": "ADR-0017",
      "statement": "Opacity, visibility, classes, clipping, transforms, computed style, renderer pixels, OBS state, delivery, and hardware state may not alter or be claimed by server-known structural visibility projection."
    },
    {
      "id": "visibility-feedback-includes-hidden-ancestors",
      "kind": "rule",
      "sourceDecision": "ADR-0017",
      "statement": "A component may be reported active only when its own known inline display state and that of every ancestor are not display none after whitespace and case normalization."
    },
    {
      "id": "visibility-feedback-projection-claims-are-bounded",
      "kind": "rule",
      "sourceDecision": "ADR-0017",
      "statement": "Passing the pure projection may not be presented as trusted provenance, clock authority, signed or authenticated delivery, three-second scheduling, acknowledgement, operation failure, reconnect recovery, renderer observation, Studio or Companion consumption, or hardware behavior."
    },
    {
      "id": "visibility-feedback-projection-fails-closed",
      "kind": "rule",
      "sourceDecision": "ADR-0017",
      "statement": "Projection must reject Show mismatch, malformed relied-upon structure, malformed descriptors, duplicate subjects or component identifiers, missing addressed components, invalid revisions or times, observation before a known snapshot update, and inputs exceeding 1,000 elements or actions without emitting partial output."
    },
    {
      "id": "visibility-feedback-projection-is-deterministic",
      "kind": "rule",
      "sourceDecision": "ADR-0017",
      "statement": "Equivalent valid inputs must produce canonically ordered equivalent observations without mutating the snapshot or catalog."
    },
    {
      "id": "workspace-license-metadata-is-consistent",
      "kind": "rule",
      "sourceDecision": "ADR-0018",
      "statement": "Every workspace manifest and lockfile workspace entry must declare Apache-2.0, and every workspace manifest must attribute Rodrigo Vicente with the canonical X URL."
    }
  ],
  "schemasHash": "7140a74320331a66d4edcb04118f77a1fa39e0a5378a8923c22fe6ef4329a0ce",
  "schemaVersion": "overlaykit-governance-plan/v2",
  "specifications": [
    {
      "contentHash": "c0dc8cd59249be7f8c2ed8abec9f686ab03f8f52efaae2b5df49b1140121213b",
      "declaredStatus": "accepted",
      "effectiveStatus": "accepted",
      "id": "SPEC-0001",
      "requirementIds": [
        "REQ-DOM-001",
        "REQ-DOM-002",
        "REQ-DOM-003",
        "REQ-DOM-004",
        "REQ-DOM-005",
        "REQ-DOM-006",
        "REQ-INT-001",
        "REQ-INT-002",
        "REQ-NAV-001",
        "REQ-NAV-002",
        "REQ-NAV-003",
        "REQ-NAV-004",
        "REQ-RUN-001",
        "REQ-RUN-002",
        "REQ-RUN-003",
        "REQ-RUN-004",
        "REQ-SEC-001",
        "REQ-SEC-002",
        "REQ-SEC-003",
        "REQ-SEC-004",
        "REQ-SEC-005"
      ],
      "supersededBy": null,
      "title": "Secure show authoring and live production",
      "userStoryIds": [
        "US-001",
        "US-002",
        "US-003",
        "US-004",
        "US-005",
        "US-006",
        "US-007",
        "US-008",
        "US-009",
        "US-010"
      ],
      "workflowIds": [
        "WF-001",
        "WF-002",
        "WF-003",
        "WF-004"
      ]
    }
  ],
  "trustAnchors": [
    {
      "checkAppId": 15368,
      "checkAppSlug": "github-actions",
      "checkName": "validate",
      "id": "github:overlaykit",
      "jobName": "validate",
      "kind": "github",
      "oidcIssuer": "https://token.actions.githubusercontent.com",
      "protectedRef": "refs/heads/main",
      "repository": "OverlayKit/overlaykit",
      "ruleset": {
        "activationChange": "CHG-0003",
        "allowAdditionalRules": false,
        "allowAdditionalRulesets": false,
        "allowBypassActors": false,
        "allowedMergeMethods": [
          "merge"
        ],
        "dismissStaleReviewsOnPush": false,
        "doNotEnforceOnCreate": false,
        "minimumApprovals": 0,
        "name": "main",
        "requireCodeOwnerReview": false,
        "requiredRules": [
          "deletion",
          "non_fast_forward",
          "pull_request",
          "required_signatures",
          "required_status_checks"
        ],
        "requiredStatusChecks": [
          "validate"
        ],
        "requireLastPushApproval": false,
        "requireReviewThreadResolution": true,
        "strictRequiredStatusChecksPolicy": true
      },
      "runnerEnvironment": "github-hosted",
      "workflowPath": ".github/workflows/governance.yml"
    }
  ]
}
